{
  "lastUpdated": "2026-04-12T01:23:33.568Z",
  "source": "Daily Prophet Auto-Update",
  "news": [
    {
      "id": 1,
      "title": "哈利-波特》系列：HBO 确认与电影的一个主要区别 - notebookcheck-cn.com",
      "date": "2026-04-11",
      "category": "影视动态",
      "summary": "哈利-波特》系列：HBO 确认与电影的一个主要区别",
      "content": "哈利-波特》系列：HBO 确认与电影的一个主要区别",
      "image": "📺",
      "relatedLinks": [
        {
          "label": "📚 原著百科",
          "path": "/books"
        },
        {
          "label": "🧙 人物百科",
          "path": "/characters"
        }
      ],
      "source": "https://news.google.com/rss/articles/CBMiYEFVX3lxTE5SbWEzOFJRa2lreFd5bk9JZFhOYmFmcXJidnpveGdLZml3Y2poMnVXRkd5V0dUblBQYjFxX3AxbmdrZDJTY2ZyNnF0T0FVMHY0a1N0QjBnbzltMkhVd1RTTQ?oc=5"
    },
    {
      "id": 2,
      "title": "我们正在搭建巨大的多套件LEGO Harry Potter Hogwarts Castle，目前进行中 - news.17173.com",
      "date": "2026-04-10",
      "category": "影视动态",
      "summary": "我们正在搭建巨大的多套件LEGO Harry Potter Hogwarts Castle，目前进行中",
      "content": "我们正在搭建巨大的多套件LEGO Harry Potter Hogwarts Castle，目前进行中",
      "image": "📺",
      "relatedLinks": [
        {
          "label": "📚 原著百科",
          "path": "/books"
        },
        {
          "label": "🧙 人物百科",
          "path": "/characters"
        }
      ],
      "source": "https://news.google.com/rss/articles/CBMiZEFVX3lxTE52ODdwMFMySlZFbUo0ZEVXeU1aUmlwVE5IYlBGMEo3N0VzaExma25WT0RLUVN1cHhGbXpIeEVwSlAyV0lsNzIzbWJ3bkg0TGhCaW5mZEgzaF9CRS1NTkZGb3dpd08?oc=5"
    },
    {
      "id": 3,
      "title": "口碑暴死？《哈利波特》新预告片被暴踩：黑人脏辫太出戏 - 直播吧",
      "date": "2026-04-10",
      "category": "影视动态",
      "summary": "口碑暴死？《哈利波特》新预告片被暴踩：黑人脏辫太出戏",
      "content": "口碑暴死？《哈利波特》新预告片被暴踩：黑人脏辫太出戏",
      "image": "📺",
      "relatedLinks": [
        {
          "label": "📚 原著百科",
          "path": "/books"
        },
        {
          "label": "🧙 人物百科",
          "path": "/characters"
        }
      ],
      "source": "https://news.google.com/rss/articles/CBMicEFVX3lxTFBiSmVGdTFJUmxISVphOUlITFFMRXR5anEwbGd2bGV1cHhEdWd2RFNBWWhBVU16Y01WTnVfcGYzWm1ubS1QRXBQYmVjb3JKZVZ5LVl0eGFsMGlvMmNmY3c4M3hRcFY3QldKVVZabnhBS0c?oc=5"
    },
    {
      "id": 4,
      "title": "我们正在搭建巨大的多套件LEGO Harry Potter Hogwarts Castle，目前进行中 - news.17173.com",
      "date": "2026-04-10",
      "category": "影视动态",
      "summary": "我们正在搭建巨大的多套件LEGO Harry Potter Hogwarts Castle，目前进行中",
      "content": "我们正在搭建巨大的多套件LEGO Harry Potter Hogwarts Castle，目前进行中",
      "image": "📺",
      "relatedLinks": [
        {
          "label": "📚 原著百科",
          "path": "/books"
        },
        {
          "label": "🧙 人物百科",
          "path": "/characters"
        }
      ],
      "source": "https://news.google.com/rss/articles/CBMiZEFVX3lxTE52ODdwMFMySlZFbUo0ZEVXeU1aUmlwVE5IYlBGMEo3N0VzaExma25WT0RLUVN1cHhGbXpIeEVwSlAyV0lsNzIzbWJ3bkg0TGhCaW5mZEgzaF9CRS1NTkZGb3dpd08?oc=5"
    },
    {
      "id": 5,
      "title": "口碑暴死？《哈利波特》新预告片被暴踩：黑人脏辫太出戏 - 直播吧",
      "date": "2026-04-10",
      "category": "影视动态",
      "summary": "口碑暴死？《哈利波特》新预告片被暴踩：黑人脏辫太出戏",
      "content": "口碑暴死？《哈利波特》新预告片被暴踩：黑人脏辫太出戏",
      "image": "📺",
      "relatedLinks": [
        {
          "label": "📚 原著百科",
          "path": "/books"
        },
        {
          "label": "🧙 人物百科",
          "path": "/characters"
        }
      ],
      "source": "https://news.google.com/rss/articles/CBMicEFVX3lxTFBiSmVGdTFJUmxISVphOUlITFFMRXR5anEwbGd2bGV1cHhEdWd2RFNBWWhBVU16Y01WTnVfcGYzWm1ubS1QRXBQYmVjb3JKZVZ5LVl0eGFsMGlvMmNmY3c4M3hRcFY3QldKVVZabnhBS0c?oc=5"
    },
    {
      "id": 6,
      "title": "我们正在搭建巨大的多套件LEGO Harry Potter Hogwarts Castle，目前进行中 - news.17173.com",
      "date": "2026-04-10",
      "category": "影视动态",
      "summary": "我们正在搭建巨大的多套件LEGO Harry Potter Hogwarts Castle，目前进行中",
      "content": "我们正在搭建巨大的多套件LEGO Harry Potter Hogwarts Castle，目前进行中",
      "image": "📺",
      "relatedLinks": [
        {
          "label": "📚 原著百科",
          "path": "/books"
        },
        {
          "label": "🧙 人物百科",
          "path": "/characters"
        }
      ],
      "source": "https://news.google.com/rss/articles/CBMiZEFVX3lxTE52ODdwMFMySlZFbUo0ZEVXeU1aUmlwVE5IYlBGMEo3N0VzaExma25WT0RLUVN1cHhGbXpIeEVwSlAyV0lsNzIzbWJ3bkg0TGhCaW5mZEgzaF9CRS1NTkZGb3dpd08?oc=5"
    },
    {
      "id": 7,
      "title": "口碑暴死？《哈利波特》新预告片被暴踩：黑人脏辫太出戏 - 直播吧",
      "date": "2026-04-10",
      "category": "影视动态",
      "summary": "口碑暴死？《哈利波特》新预告片被暴踩：黑人脏辫太出戏",
      "content": "口碑暴死？《哈利波特》新预告片被暴踩：黑人脏辫太出戏",
      "image": "📺",
      "relatedLinks": [
        {
          "label": "📚 原著百科",
          "path": "/books"
        },
        {
          "label": "🧙 人物百科",
          "path": "/characters"
        }
      ],
      "source": "https://news.google.com/rss/articles/CBMicEFVX3lxTFBiSmVGdTFJUmxISVphOUlITFFMRXR5anEwbGd2bGV1cHhEdWd2RFNBWWhBVU16Y01WTnVfcGYzWm1ubS1QRXBQYmVjb3JKZVZ5LVl0eGFsMGlvMmNmY3c4M3hRcFY3QldKVVZabnhBS0c?oc=5"
    },
    {
      "id": 8,
      "title": "我们正在搭建巨大的多套件LEGO Harry Potter Hogwarts Castle，目前进行中 - news.17173.com",
      "date": "2026-04-10",
      "category": "影视动态",
      "summary": "我们正在搭建巨大的多套件LEGO Harry Potter Hogwarts Castle，目前进行中",
      "content": "我们正在搭建巨大的多套件LEGO Harry Potter Hogwarts Castle，目前进行中",
      "image": "📺",
      "relatedLinks": [
        {
          "label": "📚 原著百科",
          "path": "/books"
        },
        {
          "label": "🧙 人物百科",
          "path": "/characters"
        }
      ],
      "source": "https://news.google.com/rss/articles/CBMiZEFVX3lxTE52ODdwMFMySlZFbUo0ZEVXeU1aUmlwVE5IYlBGMEo3N0VzaExma25WT0RLUVN1cHhGbXpIeEVwSlAyV0lsNzIzbWJ3bkg0TGhCaW5mZEgzaF9CRS1NTkZGb3dpd08?oc=5"
    },
    {
      "id": 9,
      "title": "口碑暴死？《哈利波特》新预告片被暴踩：黑人脏辫太出戏 - 直播吧",
      "date": "2026-04-10",
      "category": "影视动态",
      "summary": "口碑暴死？《哈利波特》新预告片被暴踩：黑人脏辫太出戏",
      "content": "口碑暴死？《哈利波特》新预告片被暴踩：黑人脏辫太出戏",
      "image": "📺",
      "relatedLinks": [
        {
          "label": "📚 原著百科",
          "path": "/books"
        },
        {
          "label": "🧙 人物百科",
          "path": "/characters"
        }
      ],
      "source": "https://news.google.com/rss/articles/CBMicEFVX3lxTFBiSmVGdTFJUmxISVphOUlITFFMRXR5anEwbGd2bGV1cHhEdWd2RFNBWWhBVU16Y01WTnVfcGYzWm1ubS1QRXBQYmVjb3JKZVZ5LVl0eGFsMGlvMmNmY3c4M3hRcFY3QldKVVZabnhBS0c?oc=5"
    },
    {
      "id": 10,
      "title": "我们正在搭建巨大的多套件LEGO Harry Potter Hogwarts Castle，目前进行中 - 17173",
      "date": "2026-04-10",
      "category": "影视动态",
      "summary": "我们正在搭建巨大的多套件LEGO Harry Potter Hogwarts Castle，目前进行中",
      "content": "我们正在搭建巨大的多套件LEGO Harry Potter Hogwarts Castle，目前进行中",
      "image": "📺",
      "relatedLinks": [
        {
          "label": "📚 原著百科",
          "path": "/books"
        },
        {
          "label": "🧙 人物百科",
          "path": "/characters"
        }
      ],
      "source": "https://news.google.com/rss/articles/CBMiZEFVX3lxTE52ODdwMFMySlZFbUo0ZEVXeU1aUmlwVE5IYlBGMEo3N0VzaExma25WT0RLUVN1cHhGbXpIeEVwSlAyV0lsNzIzbWJ3bkg0TGhCaW5mZEgzaF9CRS1NTkZGb3dpd08?oc=5"
    },
    {
      "id": 11,
      "title": "口碑暴死？《哈利波特》新预告片被暴踩：黑人脏辫太出戏 - 直播吧",
      "date": "2026-04-10",
      "category": "影视动态",
      "summary": "口碑暴死？《哈利波特》新预告片被暴踩：黑人脏辫太出戏",
      "content": "口碑暴死？《哈利波特》新预告片被暴踩：黑人脏辫太出戏",
      "image": "📺",
      "relatedLinks": [
        {
          "label": "📚 原著百科",
          "path": "/books"
        },
        {
          "label": "🧙 人物百科",
          "path": "/characters"
        }
      ],
      "source": "https://news.google.com/rss/articles/CBMicEFVX3lxTFBiSmVGdTFJUmxISVphOUlITFFMRXR5anEwbGd2bGV1cHhEdWd2RFNBWWhBVU16Y01WTnVfcGYzWm1ubS1QRXBQYmVjb3JKZVZ5LVl0eGFsMGlvMmNmY3c4M3hRcFY3QldKVVZabnhBS0c?oc=5"
    },
    {
      "id": 12,
      "title": "我们正在搭建巨大的多套件LEGO Harry Potter Hogwarts Castle，目前进行中 - 17173",
      "date": "2026-04-10",
      "category": "影视动态",
      "summary": "我们正在搭建巨大的多套件LEGO Harry Potter Hogwarts Castle，目前进行中",
      "content": "我们正在搭建巨大的多套件LEGO Harry Potter Hogwarts Castle，目前进行中",
      "image": "📺",
      "relatedLinks": [
        {
          "label": "📚 原著百科",
          "path": "/books"
        },
        {
          "label": "🧙 人物百科",
          "path": "/characters"
        }
      ],
      "source": "https://news.google.com/rss/articles/CBMiZEFVX3lxTE52ODdwMFMySlZFbUo0ZEVXeU1aUmlwVE5IYlBGMEo3N0VzaExma25WT0RLUVN1cHhGbXpIeEVwSlAyV0lsNzIzbWJ3bkg0TGhCaW5mZEgzaF9CRS1NTkZGb3dpd08?oc=5"
    },
    {
      "id": 13,
      "title": "口碑暴死？《哈利波特》新预告片被暴踩：黑人脏辫太出戏 - 直播吧",
      "date": "2026-04-10",
      "category": "影视动态",
      "summary": "口碑暴死？《哈利波特》新预告片被暴踩：黑人脏辫太出戏",
      "content": "口碑暴死？《哈利波特》新预告片被暴踩：黑人脏辫太出戏",
      "image": "📺",
      "relatedLinks": [
        {
          "label": "📚 原著百科",
          "path": "/books"
        },
        {
          "label": "🧙 人物百科",
          "path": "/characters"
        }
      ],
      "source": "https://news.google.com/rss/articles/CBMicEFVX3lxTFBiSmVGdTFJUmxISVphOUlITFFMRXR5anEwbGd2bGV1cHhEdWd2RFNBWWhBVU16Y01WTnVfcGYzWm1ubS1QRXBQYmVjb3JKZVZ5LVl0eGFsMGlvMmNmY3c4M3hRcFY3QldKVVZabnhBS0c?oc=5"
    },
    {
      "id": 14,
      "title": "我们正在搭建巨大的多套件LEGO Harry Potter Hogwarts Castle，目前进行中 - 17173",
      "date": "2026-04-10",
      "category": "影视动态",
      "summary": "我们正在搭建巨大的多套件LEGO Harry Potter Hogwarts Castle，目前进行中",
      "content": "我们正在搭建巨大的多套件LEGO Harry Potter Hogwarts Castle，目前进行中",
      "image": "📺",
      "relatedLinks": [
        {
          "label": "📚 原著百科",
          "path": "/books"
        },
        {
          "label": "🧙 人物百科",
          "path": "/characters"
        }
      ],
      "source": "https://news.google.com/rss/articles/CBMiZEFVX3lxTE52ODdwMFMySlZFbUo0ZEVXeU1aUmlwVE5IYlBGMEo3N0VzaExma25WT0RLUVN1cHhGbXpIeEVwSlAyV0lsNzIzbWJ3bkg0TGhCaW5mZEgzaF9CRS1NTkZGb3dpd08?oc=5"
    },
    {
      "id": 15,
      "title": "口碑暴死？《哈利波特》新预告片被暴踩：黑人脏辫太出戏 - 直播吧",
      "date": "2026-04-10",
      "category": "影视动态",
      "summary": "口碑暴死？《哈利波特》新预告片被暴踩：黑人脏辫太出戏",
      "content": "口碑暴死？《哈利波特》新预告片被暴踩：黑人脏辫太出戏",
      "image": "📺",
      "relatedLinks": [
        {
          "label": "📚 原著百科",
          "path": "/books"
        },
        {
          "label": "🧙 人物百科",
          "path": "/characters"
        }
      ],
      "source": "https://news.google.com/rss/articles/CBMicEFVX3lxTFBiSmVGdTFJUmxISVphOUlITFFMRXR5anEwbGd2bGV1cHhEdWd2RFNBWWhBVU16Y01WTnVfcGYzWm1ubS1QRXBQYmVjb3JKZVZ5LVl0eGFsMGlvMmNmY3c4M3hRcFY3QldKVVZabnhBS0c?oc=5"
    },
    {
      "id": 16,
      "title": "《哈利波特：魁地奇冠军》主演拉尔夫·费因斯称蒂尔达·斯文顿演伏地魔会“非常棒”，并坦言曾被邀回归，但如今认为“时机已过” - 17173",
      "date": "2026-04-10",
      "category": "游戏资讯",
      "summary": "《哈利波特：魁地奇冠军》主演拉尔夫·费因斯称蒂尔达·斯文顿演伏地魔会“非常棒”，并坦言曾被邀回归，但如今认为“时机已过”",
      "content": "《哈利波特：魁地奇冠军》主演拉尔夫·费因斯称蒂尔达·斯文顿演伏地魔会“非常棒”，并坦言曾被邀回归，但如今认为“时机已过”",
      "image": "🎮",
      "relatedLinks": [
        {
          "label": "🎩 分院帽测试",
          "path": "/interactive/sorting"
        },
        {
          "label": "✨ 咒语大全",
          "path": "/world/spells"
        }
      ],
      "source": "https://news.google.com/rss/articles/CBMiZEFVX3lxTE12ZTl5SmF0QTBDSWlmSzVUVkpOR2hpdnQxSGVXaXN0dHJHYnRrOElyR0s3VzNJdC1ubjd4RzFmaU55WUMwZmtLOE91LV9FNWxvTFRERmhTMFFENDM0a0NFcldTZU4?oc=5"
    },
    {
      "id": 17,
      "title": "我们正在搭建巨大的多套件LEGO Harry Potter Hogwarts Castle，目前进行中 - 17173",
      "date": "2026-04-10",
      "category": "影视动态",
      "summary": "我们正在搭建巨大的多套件LEGO Harry Potter Hogwarts Castle，目前进行中",
      "content": "我们正在搭建巨大的多套件LEGO Harry Potter Hogwarts Castle，目前进行中",
      "image": "📺",
      "relatedLinks": [
        {
          "label": "📚 原著百科",
          "path": "/books"
        },
        {
          "label": "🧙 人物百科",
          "path": "/characters"
        }
      ],
      "source": "https://news.google.com/rss/articles/CBMiZEFVX3lxTE52ODdwMFMySlZFbUo0ZEVXeU1aUmlwVE5IYlBGMEo3N0VzaExma25WT0RLUVN1cHhGbXpIeEVwSlAyV0lsNzIzbWJ3bkg0TGhCaW5mZEgzaF9CRS1NTkZGb3dpd08?oc=5"
    },
    {
      "id": 18,
      "title": "口碑暴死？《哈利波特》新预告片被暴踩：黑人脏辫太出戏 - 直播吧",
      "date": "2026-04-10",
      "category": "影视动态",
      "summary": "口碑暴死？《哈利波特》新预告片被暴踩：黑人脏辫太出戏",
      "content": "口碑暴死？《哈利波特》新预告片被暴踩：黑人脏辫太出戏",
      "image": "📺",
      "relatedLinks": [
        {
          "label": "📚 原著百科",
          "path": "/books"
        },
        {
          "label": "🧙 人物百科",
          "path": "/characters"
        }
      ],
      "source": "https://news.google.com/rss/articles/CBMicEFVX3lxTFBiSmVGdTFJUmxISVphOUlITFFMRXR5anEwbGd2bGV1cHhEdWd2RFNBWWhBVU16Y01WTnVfcGYzWm1ubS1QRXBQYmVjb3JKZVZ5LVl0eGFsMGlvMmNmY3c4M3hRcFY3QldKVVZabnhBS0c?oc=5"
    },
    {
      "id": 19,
      "title": "《哈利波特：魁地奇冠军》主演拉尔夫·费因斯称蒂尔达·斯文顿演伏地魔会“非常棒”，并坦言曾被邀回归，但如今认为“时机已过” - 17173",
      "date": "2026-04-10",
      "category": "游戏资讯",
      "summary": "《哈利波特：魁地奇冠军》主演拉尔夫·费因斯称蒂尔达·斯文顿演伏地魔会“非常棒”，并坦言曾被邀回归，但如今认为“时机已过”",
      "content": "《哈利波特：魁地奇冠军》主演拉尔夫·费因斯称蒂尔达·斯文顿演伏地魔会“非常棒”，并坦言曾被邀回归，但如今认为“时机已过”",
      "image": "🎮",
      "relatedLinks": [
        {
          "label": "🎩 分院帽测试",
          "path": "/interactive/sorting"
        },
        {
          "label": "✨ 咒语大全",
          "path": "/world/spells"
        }
      ],
      "source": "https://news.google.com/rss/articles/CBMiZEFVX3lxTE12ZTl5SmF0QTBDSWlmSzVUVkpOR2hpdnQxSGVXaXN0dHJHYnRrOElyR0s3VzNJdC1ubjd4RzFmaU55WUMwZmtLOE91LV9FNWxvTFRERmhTMFFENDM0a0NFcldTZU4?oc=5"
    },
    {
      "id": 20,
      "title": "我们正在搭建巨大的多套件LEGO Harry Potter Hogwarts Castle，目前进行中 - 17173",
      "date": "2026-04-10",
      "category": "影视动态",
      "summary": "我们正在搭建巨大的多套件LEGO Harry Potter Hogwarts Castle，目前进行中",
      "content": "我们正在搭建巨大的多套件LEGO Harry Potter Hogwarts Castle，目前进行中",
      "image": "📺",
      "relatedLinks": [
        {
          "label": "📚 原著百科",
          "path": "/books"
        },
        {
          "label": "🧙 人物百科",
          "path": "/characters"
        }
      ],
      "source": "https://news.google.com/rss/articles/CBMiZEFVX3lxTE52ODdwMFMySlZFbUo0ZEVXeU1aUmlwVE5IYlBGMEo3N0VzaExma25WT0RLUVN1cHhGbXpIeEVwSlAyV0lsNzIzbWJ3bkg0TGhCaW5mZEgzaF9CRS1NTkZGb3dpd08?oc=5"
    }
  ]
}